llama_index/storage/chat_store/mongo/__init__.py
llama_index/storage/chat_store/mongo/base.py
llama_index_storage_chat_store_mongo-0.3.0.dist-info/METADATA
llama_index_storage_chat_store_mongo-0.3.0.dist-info/WHEEL
llama_index_storage_chat_store_mongo-0.3.0.dist-info/licenses/LICENSE
llama_index_storage_chat_store_mongo-0.3.0.dist-info/RECORD
