Metadata-Version: 2.4
Name: llama-index-storage-chat-store-mongo
Version: 0.3.0
Summary: llama-index storage-chat-store mongo integration
Author-email: Vrushab Ghodke <vrushab.ghodke@gmail.com>
License-Expression: MIT
License-File: LICENSE
Requires-Python: <4.0,>=3.9
Requires-Dist: llama-index-core<0.15,>=0.13.0
Requires-Dist: pymongo<5,>=4.13.0
